csharpy/__init__.py
csharpy/binaries/__init__.py
csharpy/binaries/add_reference.py
csharpy/binaries/Release/CSharPyExtension.dll
csharpy/binaries/Release/DynamicCS.dll
csharpy/binaries/Release/Microsoft.VisualStudio.TestPlatform.MSTest.TestAdapter.dll
csharpy/binaries/Release/Microsoft.VisualStudio.TestPlatform.MSTestAdapter.PlatformServices.Interface.dll
csharpy/binaries/Release/Microsoft.VisualStudio.TestPlatform.MSTestAdapter.PlatformServices.dll
csharpy/binaries/Release/TestCSharpyCore.dll
csharpy/binaries/Release/__init__.py
csharpy/cparts/__init__.py
csharpy/notebook/__init__.py
csharpy/notebook/csmagics.py
csharpy/runtime/__init__.py
csharpy/runtime/compile.py
csharpy/sphinxext/__init__.py
csharpy/sphinxext/sphinx_runcsharp_extension.py
src/csharpy/cparts/cmodule.cp37-win_amd64.pyd
csharpy-0.1.116.dist-info/LICENSE.txt
csharpy-0.1.116.dist-info/METADATA
csharpy-0.1.116.dist-info/WHEEL
csharpy-0.1.116.dist-info/top_level.txt
csharpy-0.1.116.dist-info/RECORD
