Metadata-Version: 2.1
Name: csharpy
Version: 0.1.116
Summary: Tools to use C# + Python mostly from Python.
Home-page: http://www.xavierdupre.fr/app/csharpy/
Author: Xavier Dupré
Author-email: xavier.dupre@gmail.com
License: MIT
Download-URL: https://github.com/sdpython/csharpy/
Keywords: csharpy,first name,last name
Platform: UNKNOWN
Classifier: Programming Language :: Python :: 3
Classifier: Intended Audience :: Developers
Classifier: Topic :: Scientific/Engineering
Classifier: Topic :: Education
Classifier: License :: OSI Approved :: MIT License
Classifier: Development Status :: 5 - Production/Stable
Requires-Dist: pythonnet
Requires-Dist: pyquickhelper
